[
    {
        "name":"Honda CB350RS",
        "image":"https://encrypted-tbn0.gstatic.com/images?q=tbn:ANd9GcQnzx2mkHREs5IGyORaq3TWv2PPRGWKDQNHkg&usqp=CAU",
        "price":"130000",
        "description":"Amet minim mollit non deserunt ullamco est sit aliqua dolor do amet sint. Velit officia consequat duis enim velit mollit.",
        "quantity":"1",
        "suppliername":"santo"
    },
    {
        "name":"Yamaha YZF R15 V4",
        "image":"https://imgd.aeplcdn.com/360x202/n/cw/ec/103795/yzf-r15-right-front-three-quarter-7.jpeg?isig=0&q=75",
        "price":"150000",
        "description":"Amet minim mollit non deserunt ullamco est sit aliqua dolor do amet sint. Velit officia consequat duis enim velit mollit.",
        "quantity":"2",
        "suppliername":"shamol"
    },
    {
        "name":"TVS Apache RTR 160 4V",
        "image":"https://encrypted-tbn0.gstatic.com/images?q=tbn:ANd9GcQ-fP_d-3EFvbN5D0o1-T-xKAtsjZfgv1_TnQ&usqp=CAU",
        "price":"90000",
        "description":"Amet minim mollit non deserunt ullamco est sit aliqua dolor do amet sint. Velit officia consequat duis enim velit mollit.",
        "quantity":"3",
        "suppliername":"joy"
    },
    {
        "name":"Bajaj Pulsar 220 F",
        "image":"https://encrypted-tbn0.gstatic.com/images?q=tbn:ANd9GcS4EfUVTAFYPClVgO5zJLoxsYwLkzL1iow_N4mUKT19uhXx8WvUvV2VzMWBxGwd3oTG3K8&usqp=CAU",
        "price":"140000",
        "description":"Amet minim mollit non deserunt ullamco est sit aliqua dolor do amet sint. Velit officia consequat duis enim velit mollit.",
        "quantity":"4",
        "suppliername":"sourov"
    },
    {
        "name":"Bajaj Pulsar RS200",
        "image":"https://bd.gaadicdn.com/processedimages/bajaj/bajaj-pulsar-rs-200/494X300/bajaj-pulsar-rs-2005fd990850af47.jpg?imwidth=380&impolicy=resize",
        "price":"160000",
        "description":"Amet minim mollit non deserunt ullamco est sit aliqua dolor do amet sint. Velit officia consequat duis enim velit mollit.",
        "quantity":"5",
        "suppliername":"soboj"
    },
    {
        "name":"Hero Glamour",
        "image":"https://imgd.aeplcdn.com/1056x594/n/cw/ec/50100/glamour-right-front-three-quarter.jpeg?q=75",
        "price":"850000",
        "description":"Amet minim mollit non deserunt ullamco est sit aliqua dolor do amet sint. Velit officia consequat duis enim velit mollit.",
        "quantity":"6",
        "suppliername":"porlok"
    },
    {
        "name":"Hero Super Splendor",
        "image":"https://media.zigcdn.com/media/model/2021/Jul/front-right-view-1811389298_600x400.jpg",
        "price":"750000",
        "description":"Amet minim mollit non deserunt ullamco est sit aliqua dolor do amet sint. Velit officia consequat duis enim velit mollit.",
        "quantity":"7",
        "suppliername":"topon"
    },
    {
        "name":"Yamaha YZF-R3",
        "image":"https://i.ndtvimg.com/i/2016-06/yamaha-r3_827x510_61467287743.jpg",
        "price":"160000",
        "description":"Amet minim mollit non deserunt ullamco est sit aliqua dolor do amet sint. Velit officia consequat duis enim velit mollit.",
        "quantity":"8",
        "suppliername":"posanto"
    },
    {
        "name":"Suzuki Gixxer",
        "image":"https://bd.gaadicdn.com/processedimages/suzuki/2019-gixxer-sf/494X300/2019-gixxer-sf5f758c0538484.jpg?imwidth=380&impolicy=resize",
        "price":"300000",
        "description":"Amet minim mollit non deserunt ullamco est sit aliqua dolor do amet sint. Velit officia consequat duis enim velit mollit.",
        "quantity":"9",
        "suppliername":"milon"
    },
    {
        "name":"Hero Glamour Bs6",
        "image":"https://bikeindia.in/wp-content/uploads/2020/04/2020-Hero-Glamour-125-BS6-Bike-India-first-ride-review-specs-and-price-5.jpg",
        "price":"800000",
        "description":"Amet minim mollit non deserunt ullamco est sit aliqua dolor do amet sint. Velit officia consequat duis enim velit mollit.",
        "quantity":"10",
        "suppliername":"bokul"
    },
    {
        "name":"Bajaj Discover 125",
        "image":"https://4.imimg.com/data4/JW/BC/GLADMIN-10639468/1-500x500.jpg",
        "price":"100000",
        "description":"Amet minim mollit non deserunt ullamco est sit aliqua dolor do amet sint. Velit officia consequat duis enim velit mollit.",
        "quantity":"11",
        "suppliername":"shuvo"
    },
    {
        "name":"Yamaha MT-15",
        "image":"https://bd.gaadicdn.com/processedimages/yamaha/mt-15-2-0/640X309/mt-15-2-062541199845ed.jpg?tr=w-135",
        "price":"130000",
        "description":"Amet minim mollit non deserunt ullamco est sit aliqua dolor do amet sint. Velit officia consequat duis enim velit mollit.",
        "quantity":"1",
        "suppliername":"potik"
    }
]